Metadata-Version: 2.1
Name: parsyc
Version: 1.0
Summary: A Haskell/Parsec inspired Parser Combinator library
Home-page: https://github.com/mustafaquraish/marker
Author: Mustafa Quraish
Author-email: mustafa@cs.toronto.edu
License: MIT
Platform: UNKNOWN
Classifier: Programming Language :: Python :: 3
Classifier: License :: OSI Approved :: MIT License
Classifier: Operating System :: Unix
